{"_type":"export","__export_format":4,"__export_date":"2022-03-18T02:32:11.271Z","__export_source":"insomnia.desktop.app:v2022.2.0","resources":[{"_id":"req_1cb6dbde9df14e7794818f186abd4f87","parentId":"wrk_32f8fbd6936346018aa79271c1953e83","modified":1647568004821,"created":1647567940380,"url":"https://localhost:44338/v1/api/Passageiros","name":"Obter todos","description":"","method":"GET","body":{},"parameters":[],"headers":[],"authentication":{},"metaSortKey":-1647567919244,"isPrivate":false,"settingStoreCookies":true,"settingSendCookies":true,"settingDisableRenderRequestBody":true,"settingEncodeUrl":true,"settingRebuildPath":true,"settingFollowRedirects":"global","_type":"request"},{"_id":"wrk_32f8fbd6936346018aa79271c1953e83","parentId":null,"modified":1647567522888,"created":1647567522888,"name":"AeroAPI","description":"","scope":"collection","_type":"workspace"},{"_id":"req_fc55857c178540fc9aeabc9e3710683b","parentId":"wrk_32f8fbd6936346018aa79271c1953e83","modified":1647570157537,"created":1647567919194,"url":"https://localhost:44338/v1/api/Passageiros/id/1","name":"Obter único","description":"","method":"GET","body":{},"parameters":[],"headers":[],"authentication":{},"metaSortKey":-1647567919194,"isPrivate":false,"settingStoreCookies":true,"settingSendCookies":true,"settingDisableRenderRequestBody":false,"settingEncodeUrl":true,"settingRebuildPath":true,"settingFollowRedirects":"global","_type":"request"},{"_id":"req_6bb8cc3bb101425a926a79d6b4698104","parentId":"wrk_32f8fbd6936346018aa79271c1953e83","modified":1647570309375,"created":1647568184362,"url":"https://localhost:44338/v1/api/Passageiros/id/1","name":"Deletar","description":"","method":"DELETE","body":{},"parameters":[],"headers":[],"authentication":{},"metaSortKey":-1647567728508,"isPrivate":false,"settingStoreCookies":true,"settingSendCookies":true,"settingDisableRenderRequestBody":false,"settingEncodeUrl":true,"settingRebuildPath":true,"settingFollowRedirects":"global","_type":"request"},{"_id":"req_46a0e6350b094da09f8d8be3efc8e0aa","parentId":"wrk_32f8fbd6936346018aa79271c1953e83","modified":1647570545355,"created":1647568208882,"url":"https://localhost:44338/v1/api/Passageiros","name":"Inserir","description":"","method":"POST","body":{"mimeType":"application/json","text":"{\n\t\"nome\":\"Marcio\",\n\t\"idade\": 44,\n\t\"celular\": \"199988845\"\n}"},"parameters":[],"headers":[{"name":"Content-Type","value":"application/json","id":"pair_496a7f74729d4669bb0fcfcc8c2e11a3"}],"authentication":{},"metaSortKey":-1647567633165,"isPrivate":false,"settingStoreCookies":true,"settingSendCookies":true,"settingDisableRenderRequestBody":false,"settingEncodeUrl":true,"settingRebuildPath":true,"settingFollowRedirects":"global","_type":"request"},{"_id":"req_a5eb535830a648569f21edb608a94b93","parentId":"wrk_32f8fbd6936346018aa79271c1953e83","modified":1647570705001,"created":1647567537822,"url":"https://localhost:44338/v1/api/Passageiros/id/6","name":"Alterar","description":"","method":"PUT","body":{"mimeType":"application/json","text":"{\n\t\"id\": 6,\n\t\"nome\": \"Maria de Lurdes\",\n\t\"idade\": 100,\n\t\"celular\": \"1684845421\"\n}"},"parameters":[],"headers":[{"name":"Content-Type","value":"application/json","id":"pair_bb9a923a03084007be61679b1f655b95"}],"authentication":{},"metaSortKey":-1647567537822,"isPrivate":false,"settingStoreCookies":true,"settingSendCookies":true,"settingDisableRenderRequestBody":false,"settingEncodeUrl":true,"settingRebuildPath":true,"settingFollowRedirects":"global","_type":"request"},{"_id":"env_442989415eaa10bd7cbfdb651ed4365b9fac6f5d","parentId":"wrk_32f8fbd6936346018aa79271c1953e83","modified":1647567522893,"created":1647567522893,"name":"Base Environment","data":{},"dataPropertyOrder":null,"color":null,"isPrivate":false,"metaSortKey":1647567522893,"_type":"environment"},{"_id":"jar_442989415eaa10bd7cbfdb651ed4365b9fac6f5d","parentId":"wrk_32f8fbd6936346018aa79271c1953e83","modified":1647567522895,"created":1647567522895,"name":"Default Jar","cookies":[],"_type":"cookie_jar"},{"_id":"spc_79e6226e215a4bd1b8ff92e31ec2cf9b","parentId":"wrk_32f8fbd6936346018aa79271c1953e83","modified":1647567522889,"created":1647567522889,"fileName":"AeroAPI","contents":"","contentType":"yaml","_type":"api_spec"}]}